README.txt
setup.cfg
setup.py
PyMunkTMX.egg-info/PKG-INFO
PyMunkTMX.egg-info/SOURCES.txt
PyMunkTMX.egg-info/dependency_links.txt
PyMunkTMX.egg-info/requires.txt
PyMunkTMX.egg-info/top_level.txt
pymunktmx/__init__.py
pymunktmx/shapeloader.py