Metadata-Version: 1.1
Name: PyMunkTMX
Version: 0.5.3
Summary: Load shapes from Tiled maps as pymunk objects.
Home-page: https://github.com/wkmanire/PyMunkTMX
Author: William Kevin Manire <williamkmanire@gmail.com>
Author-email: williamkmanire@gmail.com
License: LGPLv3
Platform: UNKNOWN
Classifier: Intended Audience :: Developers
Classifier: Development Status :: 4 - Beta
Classifier: License :: OSI Approved :: GNU Lesser General Public License v3 (LGPLv3)
Classifier: Programming Language :: Python :: 2.7
Classifier: Topic :: Games/Entertainment
Classifier: Topic :: Software Development :: Libraries :: pygame
